AstronomyCalc/__init__.py
AstronomyCalc/basic_functions.py
AstronomyCalc/constants.py
AstronomyCalc/cosmo_calculator.py
AstronomyCalc/cosmo_equations.py
AstronomyCalc/create_data.py
AstronomyCalc/io_functions.py
AstronomyCalc/mcmc.py
AstronomyCalc/param.py
AstronomyCalc/plotting_tools.py
AstronomyCalc/input_data/README.rst
AstronomyCalc/input_data/hubble1929.csv
AstronomyCalc/input_data/hubble1929.pkl
AstronomyCalc/input_data/hubble1929.txt
AstronomyCalc/input_data/PantheonPlus/Pantheon+SH0ES.dat
AstronomyCalc/input_data/PantheonPlus/Pantheon+SH0ES_STAT+SYS.cov
AstronomyCalc/input_data/PantheonPlus/README.md
AstronomyCalc/input_data/SPARC_Galaxy_Rotmod/CamB_rotmod.dat
AstronomyCalc/input_data/SPARC_Galaxy_Rotmod/D512-2_rotmod.dat
AstronomyCalc/input_data/SPARC_Galaxy_Rotmod/D564-8_rotmod.dat
AstronomyCalc/input_data/SPARC_Galaxy_Rotmod/D631-7_rotmod.dat
AstronomyCalc/input_data/SPARC_Galaxy_Rotmod/DDO064_rotmod.dat
AstronomyCalc/input_data/SPARC_Galaxy_Rotmod/DDO154_rotmod.dat
AstronomyCalc/input_data/SPARC_Galaxy_Rotmod/DDO161_rotmod.dat
AstronomyCalc/input_data/SPARC_Galaxy_Rotmod/DDO168_rotmod.dat
AstronomyCalc/input_data/SPARC_Galaxy_Rotmod/DDO170_rotmod.dat
AstronomyCalc/input_data/SPARC_Galaxy_Rotmod/ESO079-G014_rotmod.dat
AstronomyCalc/input_data/SPARC_Galaxy_Rotmod/ESO116-G012_rotmod.dat
AstronomyCalc/input_data/SPARC_Galaxy_Rotmod/ESO444-G084_rotmod.dat
AstronomyCalc/input_data/SPARC_Galaxy_Rotmod/ESO563-G021_rotmod.dat
AstronomyCalc/input_data/SPARC_Galaxy_Rotmod/F561-1_rotmod.dat
AstronomyCalc/input_data/SPARC_Galaxy_Rotmod/F563-1_rotmod.dat
AstronomyCalc/input_data/SPARC_Galaxy_Rotmod/F563-V1_rotmod.dat
AstronomyCalc/input_data/SPARC_Galaxy_Rotmod/F563-V2_rotmod.dat
AstronomyCalc/input_data/SPARC_Galaxy_Rotmod/F565-V2_rotmod.dat
AstronomyCalc/input_data/SPARC_Galaxy_Rotmod/F567-2_rotmod.dat
AstronomyCalc/input_data/SPARC_Galaxy_Rotmod/F568-1_rotmod.dat
AstronomyCalc/input_data/SPARC_Galaxy_Rotmod/F568-3_rotmod.dat
AstronomyCalc-1.1.1.dist-info/LICENSE
AstronomyCalc-1.1.1.dist-info/METADATA
AstronomyCalc-1.1.1.dist-info/WHEEL
AstronomyCalc-1.1.1.dist-info/top_level.txt
AstronomyCalc-1.1.1.dist-info/RECORD
