Metadata-Version: 2.1
Name: AstronomyCalc
Version: 1.1.1
Author: Sambit Giri
Author-email: sambit.giri@gmail.com
License-File: LICENSE
Requires-Dist: numpy
Requires-Dist: scipy
Requires-Dist: matplotlib
Requires-Dist: pytest
Requires-Dist: astropy
Requires-Dist: astroML
Requires-Dist: pandas
Requires-Dist: emcee
Requires-Dist: corner
Requires-Dist: wget
Requires-Dist: joblib
Requires-Dist: tqdm
Requires-Dist: corner
Requires-Dist: jupyter
